<keymap version="1" name="GNOME copy Proper Redo" parent="Default for GNOME">
  <action id="$Redo">
    <keyboard-shortcut first-keystroke="shift ctrl z" />
    <keyboard-shortcut first-keystroke="shift alt back_space" />
    <keyboard-shortcut first-keystroke="ctrl y" />
  </action>
  <action id="ChangesView.Rename">
    <keyboard-shortcut first-keystroke="shift f6" />
  </action>
  <action id="Console.TableResult.NavigateAction" />
  <action id="DSM.OpenInEditor" />
  <action id="Debugger.EditFrameSource" />
  <action id="Diff.NextChange" />
  <action id="Diff.PrevChange" />
  <action id="DomCollectionControl.Edit" />
  <action id="DomElementsTreeView.GotoDomElementDeclarationAction" />
  <action id="EditSource" />
  <action id="EditorDeleteLine" />
  <action id="ExternalSystem.OpenConfig" />
  <action id="FileStructurePopup">
    <keyboard-shortcut first-keystroke="ctrl f12" />
    <keyboard-shortcut first-keystroke="shift alt 1" />
  </action>
  <action id="Find">
    <keyboard-shortcut first-keystroke="ctrl f" />
    <keyboard-shortcut first-keystroke="shift alt 3" />
    <keyboard-shortcut first-keystroke="alt f" />
  </action>
  <action id="FindNext">
    <keyboard-shortcut first-keystroke="ctrl l" />
  </action>
  <action id="FindUsages">
    <keyboard-shortcut first-keystroke="shift alt 7" />
    <keyboard-shortcut first-keystroke="f3" />
  </action>
  <action id="ForceRunToCursor">
    <keyboard-shortcut first-keystroke="ctrl alt 9" />
    <keyboard-shortcut first-keystroke="f6" />
  </action>
  <action id="GotoNextError" />
  <action id="Graph.Faces.OpenSelectedPages" />
  <action id="Jdbc.OpenEditor" />
  <action id="JumpToLastChange">
    <keyboard-shortcut first-keystroke="shift ctrl back_space" />
    <keyboard-shortcut first-keystroke="alt left" />
    <keyboard-shortcut first-keystroke="alt h" />
  </action>
  <action id="JumpToNextChange">
    <keyboard-shortcut first-keystroke="alt right" />
    <keyboard-shortcut first-keystroke="alt l" />
  </action>
  <action id="Move" />
  <action id="NavBar-navigate" />
  <action id="NextTab" />
  <action id="OpenModuleSettings" />
  <action id="PreviousTab" />
  <action id="ProjectViewChangeView">
    <keyboard-shortcut first-keystroke="alt f1" />
  </action>
  <action id="ProjectViewEditSource" />
  <action id="RemoteHostView.EditSource" />
  <action id="RenameElement">
    <keyboard-shortcut first-keystroke="shift alt r" />
    <keyboard-shortcut first-keystroke="f2" />
  </action>
  <action id="Replace">
    <keyboard-shortcut first-keystroke="ctrl r" />
    <keyboard-shortcut first-keystroke="alt r" />
  </action>
  <action id="RerunTests" />
  <action id="Scala.ShowImplicits">
    <keyboard-shortcut first-keystroke="shift ctrl alt equals" />
    <keyboard-shortcut first-keystroke="shift ctrl alt add" />
  </action>
  <action id="SelectIn">
    <keyboard-shortcut first-keystroke="alt f1" />
  </action>
  <action id="Sql.EditParameter" />
  <action id="ToggleZenMode">
    <keyboard-shortcut first-keystroke="shift ctrl f11" />
  </action>
  <action id="TypeHierarchy">
    <keyboard-shortcut first-keystroke="ctrl h" />
    <keyboard-shortcut first-keystroke="f4" />
  </action>
  <action id="Vcs.EditSource" />
  <action id="XDebugger.JumpToSource" />
</keymap>